olivertwist/__init__.py
olivertwist/config/__init__.py
olivertwist/config/configurator.py
olivertwist/config/io.py
olivertwist/config/model.py
olivertwist/main.py
olivertwist/manifest.py
olivertwist/metricengine/__init__.py
olivertwist/metricengine/engine.py
olivertwist/metricengine/result.py
olivertwist/reporter/__init__.py
olivertwist/reporter/adapter.py
olivertwist/reporter/html/css/all.min.css
olivertwist/reporter/html/css/oliver_twist.css
olivertwist/reporter/html/images/oliver_twist_logo.svg
olivertwist/reporter/html/webfonts/fa-brands-400.eot
olivertwist/reporter/html/webfonts/fa-brands-400.svg
olivertwist/reporter/html/webfonts/fa-brands-400.ttf
olivertwist/reporter/html/webfonts/fa-brands-400.woff
olivertwist/reporter/html/webfonts/fa-brands-400.woff2
olivertwist/reporter/html/webfonts/fa-regular-400.eot
olivertwist/reporter/html/webfonts/fa-regular-400.svg
olivertwist/reporter/html/webfonts/fa-regular-400.ttf
olivertwist/reporter/html/webfonts/fa-regular-400.woff
olivertwist/reporter/html/webfonts/fa-regular-400.woff2
olivertwist/reporter/html/webfonts/fa-solid-900.eot
olivertwist/reporter/html/webfonts/fa-solid-900.svg
olivertwist/reporter/html/webfonts/fa-solid-900.ttf
olivertwist/reporter/html/webfonts/fa-solid-900.woff
olivertwist/reporter/html/webfonts/fa-solid-900.woff2
olivertwist/reporter/model.py
olivertwist/reporter/reporter.py
olivertwist/reporter/templates/base.html
olivertwist/reporter/templates/index.html
olivertwist/reporter/templates/macros.jinja
olivertwist/reporter/templates/model.html
olivertwist/reporter/templates/nav_bar.html
olivertwist/reporter/terminal.py
olivertwist/ruleengine/__init__.py
olivertwist/ruleengine/discovery.py
olivertwist/ruleengine/engine.py
olivertwist/ruleengine/result.py
olivertwist/ruleengine/rule.py
olivertwist/rules/__init__.py
olivertwist/rules/no_disabled_models.py
olivertwist/rules/no_orphaned_models.py
olivertwist/rules/no_owner_on_physical_models.py
olivertwist-0.2.dist-info/entry_points.txt
olivertwist-0.2.dist-info/LICENSE
olivertwist-0.2.dist-info/WHEEL
olivertwist-0.2.dist-info/METADATA
olivertwist-0.2.dist-info/RECORD
