Metadata-Version: 2.1
Name: olivertwist
Version: 0.2
Summary: DBT DAG Auditor
Home-page: http://olivertwi.st
License: Apache-2.0
Author: Angelos Georgiadis
Author-email: angelos.georgiadis@autotrader.co.uk
Requires-Python: >=3.6,<4.0
Classifier: License :: OSI Approved :: Apache Software License
Classifier: Programming Language :: Python :: 3
Classifier: Programming Language :: Python :: 3.6
Classifier: Programming Language :: Python :: 3.7
Classifier: Programming Language :: Python :: 3.8
Classifier: Programming Language :: Python :: 3.9
Requires-Dist: Jinja2 (==2.11.2)
Requires-Dist: PyInquirer (>=1.0.3,<2.0.0)
Requires-Dist: PyYAML (>=5.3.1,<6.0.0)
Requires-Dist: click (>=7.1.2,<8.0.0)
Requires-Dist: colorama (<0.4.4)
Requires-Dist: dataclasses (>=0.8,<0.9); python_version >= "3.6" and python_version < "3.7"
Requires-Dist: dataclasses-jsonschema (>=2.13.0,<3.0.0)
Requires-Dist: flake8-bugbear (>=20.11.1,<21.0.0)
Requires-Dist: networkx (>=2.5,<3.0)
Project-URL: Repository, https://github.com/autotraderuk/oliver-twist
